LICENSE
MANIFEST.in
README.md
f2format.py
pyproject.toml
setup.cfg
setup.py
bpc_f2format.egg-info/PKG-INFO
bpc_f2format.egg-info/SOURCES.txt
bpc_f2format.egg-info/dependency_links.txt
bpc_f2format.egg-info/entry_points.txt
bpc_f2format.egg-info/requires.txt
bpc_f2format.egg-info/top_level.txt
docs/source/conf.py
scripts/find_version.py
test/test_0.py
test/test_1.py
test/test_2.py
test/test_3.py
test/test_4.py
test/test_5.py
test/test_6.py
test/test_7.py
test/test_8.py
test/test_9.py
test/test_driver.py