Metadata-Version: 2.1
Name: bpc-f2format
Version: 0.8.7
Summary: Back-port compiler for Python 3.6 formatted string (f-string) literals.
Home-page: https://github.com/pybpc/f2format
Author: Jarry Shaw
Author-email: jarryshaw@icloud.com
License: MIT
Keywords: fstring format conversion
Classifier: Development Status :: 5 - Production/Stable
Classifier: Intended Audience :: Developers
Classifier: Intended Audience :: Information Technology
Classifier: License :: OSI Approved :: MIT License
Classifier: Operating System :: OS Independent
Classifier: Programming Language :: Python :: 3.4
Classifier: Programming Language :: Python :: 3.5
Classifier: Programming Language :: Python :: 3.6
Classifier: Programming Language :: Python :: 3.7
Classifier: Programming Language :: Python :: 3.8
Classifier: Programming Language :: Python :: 3.9
Classifier: Programming Language :: Python :: 3 :: Only
Classifier: Topic :: Software Development
Classifier: Topic :: Utilities
Classifier: Typing :: Typed
Requires-Python: >=3.4
Provides-Extra: lint
Provides-Extra: test
Provides-Extra: docs
License-File: LICENSE
